{
  "vite/modulepreload-polyfill": [],
  "node_modules/.pnpm/@unocss+reset@0.44.7/node_modules/@unocss/reset/tailwind.css": [],
  "src/styles/main.css": [],
  "src/styles/prose.css": [],
  "src/styles/markdown.css": [],
  "../../../../../__uno.css": [],
  "\u0000vite/preload-helper": [],
  "node_modules/.pnpm/@vue+shared@3.2.37/node_modules/@vue/shared/dist/shared.esm-bundler.js": [],
  "node_modules/.pnpm/@vue+reactivity@3.2.37/node_modules/@vue/reactivity/dist/reactivity.esm-bundler.js": [],
  "node_modules/.pnpm/@vue+runtime-core@3.2.37/node_modules/@vue/runtime-core/dist/runtime-core.esm-bundler.js": [],
  "node_modules/.pnpm/@vue+runtime-dom@3.2.37/node_modules/@vue/runtime-dom/dist/runtime-dom.esm-bundler.js": [],
  "node_modules/.pnpm/@vueuse+shared@8.9.4_vue@3.2.37/node_modules/@vueuse/shared/index.mjs": [],
  "node_modules/.pnpm/@vueuse+core@8.9.4_vue@3.2.37/node_modules/@vueuse/core/index.mjs": [],
  "src/components/Plum.vue?vue&type=script&setup=props&lang.ts": [],
  "node_modules/.pnpm/vue-router@4.1.2_vue@3.2.37/node_modules/vue-router/dist/vue-router.mjs": [],
  "\u0000commonjsHelpers.js": [],
  "\u0000/Users/xubohua/Desktop/TEST/xubh.top/node_modules/.pnpm/dayjs@1.11.4/node_modules/dayjs/dayjs.min.js?commonjs-module": [],
  "node_modules/.pnpm/dayjs@1.11.4/node_modules/dayjs/dayjs.min.js": [],
  "src/logics/index.ts": [],
  "src/components/Post.vue?vue&type=script&setup=true&lang.ts": [],
  "node_modules/.pnpm/@vueuse+head@0.7.0_vue@3.2.37/node_modules/@vueuse/head/dist/index.mjs": [],
  "pages/index.md": [],
  "../../../../../@vite-plugin-pages/generated-pages?id=pages-generated": [],
  "\u0000/Users/xubohua/Desktop/TEST/xubh.top/node_modules/.pnpm/nprogress@0.2.0/node_modules/nprogress/nprogress.js?commonjs-module": [],
  "node_modules/.pnpm/nprogress@0.2.0/node_modules/nprogress/nprogress.js": [],
  "node_modules/.pnpm/vite-ssg@0.20.2_dfce3c2372e26d7372d40f792dd087cd/node_modules/vite-ssg/dist/chunks/state.mjs": [],
  "node_modules/.pnpm/vite-ssg@0.20.2_dfce3c2372e26d7372d40f792dd087cd/node_modules/vite-ssg/dist/chunks/ClientOnly.mjs": [],
  "node_modules/.pnpm/vite-ssg@0.20.2_dfce3c2372e26d7372d40f792dd087cd/node_modules/vite-ssg/dist/index.mjs": [],
  "\u0000/Users/xubohua/Desktop/TEST/xubh.top/node_modules/.pnpm/dayjs@1.11.4/node_modules/dayjs/plugin/localizedFormat.js?commonjs-module": [],
  "node_modules/.pnpm/dayjs@1.11.4/node_modules/dayjs/plugin/localizedFormat.js": [],
  "\u0000plugin-vue:export-helper": [],
  "src/components/Footer.vue": [],
  "~icons/ri/sun-line": [],
  "~icons/ri/moon-line": [],
  "src/components/ToggleTheme.vue?vue&type=script&setup=true&lang.ts": [],
  "src/components/Logo.vue?vue&type=style&index=0&scoped=10f99b2b&lang.css": [],
  "src/components/Logo.vue": [],
  "src/components/NavBar.vue?vue&type=style&index=0&scoped=2aa5d29f&lang.css": [],
  "src/components/NavBar.vue": [],
  "src/App.vue?vue&type=script&setup=true&lang.ts": [],
  "src/main.ts": [],
  "index.html": [],
  "assets/app.b53e5933.js-unocss-hash.css": [],
  "pages/Jottings.md": [
    "/assets/Jottings.f6777043.js"
  ],
  "src/components/AppLink.vue?vue&type=script&setup=true&lang.ts": [
    "/assets/SubNav.vue_vue_type_script_setup_true_lang.99cb14bb.js"
  ],
  "src/components/ListPosts.vue?vue&type=script&setup=true&lang.ts": [
    "/assets/SubNav.vue_vue_type_script_setup_true_lang.99cb14bb.js"
  ],
  "src/components/SubNav.vue?vue&type=script&setup=true&lang.ts": [
    "/assets/SubNav.vue_vue_type_script_setup_true_lang.99cb14bb.js"
  ],
  "pages/Vue.md": [
    "/assets/Vue.e0bc7352.js"
  ],
  "pages/[...404].md": [
    "/assets/_...404_.02cc9411.js"
  ],
  "pages/blogroll.md": [
    "/assets/blogroll.ef9a5153.js"
  ],
  "pages/bookmarks.md": [
    "/assets/bookmarks.072caba9.js"
  ],
  "src/components/icons/Vitest.vue": [
    "/assets/projects.10236c95.js",
    "/assets/projects.e1746190.css"
  ],
  "src/components/icons/Unocss.vue": [
    "/assets/projects.10236c95.js",
    "/assets/projects.e1746190.css"
  ],
  "src/components/icons/VueDemi.vue": [
    "/assets/projects.10236c95.js",
    "/assets/projects.e1746190.css"
  ],
  "src/components/icons/VueReactivity.vue": [
    "/assets/projects.10236c95.js",
    "/assets/projects.e1746190.css"
  ],
  "src/components/icons/VueUse.vue": [
    "/assets/projects.10236c95.js",
    "/assets/projects.e1746190.css"
  ],
  "src/components/icons/Slidev.vue": [
    "/assets/projects.10236c95.js",
    "/assets/projects.e1746190.css"
  ],
  "src/components/ListProjects.vue?vue&type=script&setup=true&lang.ts": [
    "/assets/projects.10236c95.js",
    "/assets/projects.e1746190.css"
  ],
  "src/components/ListProjects.vue?vue&type=style&index=0&scoped=18c53f65&lang.css": [
    "/assets/projects.10236c95.js",
    "/assets/projects.e1746190.css"
  ],
  "src/components/ListProjects.vue": [
    "/assets/projects.10236c95.js",
    "/assets/projects.e1746190.css"
  ],
  "pages/projects.md": [
    "/assets/projects.10236c95.js",
    "/assets/projects.e1746190.css"
  ],
  "pages/react.md": [
    "/assets/react.974e0e3f.js"
  ],
  "pages/wechat.md": [
    "/assets/wechat.a54cb59f.js"
  ],
  "pages/links/chat-zh.md": [
    "/assets/chat-zh.8591f08c.js"
  ],
  "pages/posts/CompoundComponents.md": [
    "/assets/CompoundComponents.2301a52b.js"
  ],
  "pages/posts/Context.md": [
    "/assets/Context.c1c43094.js"
  ],
  "pages/posts/Css in Js.md": [
    "/assets/Css in Js.7ab9204d.js"
  ],
  "pages/posts/GSAP.md": [
    "/assets/GSAP.fcce64cd.js"
  ],
  "pages/posts/ReactNactive.md": [
    "/assets/ReactNactive.bddd80c6.js"
  ],
  "../../../../../endlog.jpg": [
    "/assets/animatedsvglogo.e8c19440.js"
  ],
  "pages/posts/animatedsvglogo.md": [
    "/assets/animatedsvglogo.e8c19440.js"
  ],
  "pages/posts/flipclock.md": [
    "/assets/flipclock.43a80e58.js"
  ],
  "pages/posts/index.md": [
    "/assets/index.b752daf5.js"
  ],
  "pages/posts/jottingsl.md": [
    "/assets/jottingsl.33d5443b.js"
  ],
  "pages/posts/jottingsoo.md": [
    "/assets/jottingsoo.668ff514.js"
  ],
  "pages/posts/leetcode2283.md": [
    "/assets/leetcode2283.fca3782d.js"
  ],
  "pages/posts/memoization.md": [
    "/assets/memoization.53c40a65.js"
  ],
  "pages/posts/networksecurity.md": [
    "/assets/networksecurity.d70518de.js"
  ],
  "pages/posts/propsdaring.md": [
    "/assets/propsdaring.fdebbac0.js"
  ],
  "pages/posts/react_toolkit.md": [
    "/assets/react_toolkit.35931c8e.js"
  ],
  "pages/posts/reducer.md": [
    "/assets/reducer.53a4a9f8.js"
  ],
  "pages/posts/reduceroo.md": [
    "/assets/reduceroo.2e374cad.js"
  ],
  "pages/posts/reviewcanvas.md": [
    "/assets/reviewcanvas.bd91f5d9.js"
  ],
  "pages/posts/rolldice.md": [
    "/assets/rolldice.15386575.js"
  ],
  "pages/posts/romanticui.md": [
    "/assets/romanticui.b152ee0b.js"
  ],
  "pages/posts/types.md": [
    "/assets/types.acf7aab3.js"
  ],
  "pages/posts/useContextuseReducer.md": [
    "/assets/useContextuseReducer.191675a1.js"
  ],
  "pages/posts/useStateoo.md": [
    "/assets/useStateoo.e4892ddd.js"
  ],
  "pages/posts/vue2tovue3.md": [
    "/assets/vue2tovue3.d64f86bb.js"
  ],
  "pages/posts/weather.md": [
    "/assets/weather.236e4f2b.js"
  ],
  "pages/posts/whybreakingccinjs.md": [
    "/assets/whybreakingccinjs.9ea34d16.js"
  ]
}